fastmodules/__init__.py
fastmodules-1.1.1.dist-info/METADATA
fastmodules-1.1.1.dist-info/WHEEL
fastmodules-1.1.1.dist-info/top_level.txt
fastmodules-1.1.1.dist-info/RECORD
