Metadata-Version: 2.4
Name: fastmodules
Version: 1.1.1
Summary: Downloads most used modules
Requires-Dist: BeautifulSoup4
Requires-Dist: pyTelegramBotAPI
Requires-Dist: flask
Requires-Dist: keyboard
Requires-Dist: pyautogui
Requires-Dist: requests
Requires-Dist: numpy
Requires-Dist: pillow
Requires-Dist: pandas
Requires-Dist: mouse
Dynamic: description
Dynamic: requires-dist
Dynamic: summary
